aio_service_caller/__init__.py
aio_service_caller/discovery/__init__.py
aio_service_caller/discovery/interface.py
aio_service_caller/discovery/nacos_discovery.py
aio_service_caller/discovery/nacos_registry.py
aio_service_caller/discovery/registry_thread_loop.py
aio_service_caller/http/__init__.py
aio_service_caller/http/service_template.py
aio_service_caller/interceptor/__init__.py
aio_service_caller/interceptor/context.py
aio_service_caller/interceptor/interface.py
aio_service_caller/interceptor/service_interceptors.py
aio_service_caller/load_balancer/__init__.py
aio_service_caller/load_balancer/interface.py
aio_service_caller/load_balancer/load_balaner_factory.py
aio_service_caller/load_balancer/strategies.py
aio_service_caller/manager/__init__.py
aio_service_caller/manager/service_manager.py
aio_service_caller/models/__init__.py
aio_service_caller/models/loadbalancer_enum.py
aio_service_caller/models/nacos_service_config.py
aio_service_caller/models/service_instance.py
aio_service_caller/utils/__init__.py
aio_service_caller/utils/rw_lock.py
aio_service_caller-0.1.15.dist-info/METADATA
aio_service_caller-0.1.15.dist-info/WHEEL
aio_service_caller-0.1.15.dist-info/RECORD
