Metadata-Version: 2.4
Name: aio-service-caller
Version: 0.1.15
Summary: An async service invocation framework with registry, discovery, load balancing, and declarative HTTP client features.
Author-email: ferdinand <gongjpa@gmail.com>
License: MIT
Keywords: aio,config,load balancing,nacos,service discovery,service registry
Classifier: Development Status :: 5 - Production/Stable
Classifier: Framework :: AsyncIO
Classifier: Intended Audience :: Developers
Classifier: License :: OSI Approved :: MIT License
Classifier: Operating System :: OS Independent
Classifier: Programming Language :: Python :: 3
Classifier: Programming Language :: Python :: 3.8
Classifier: Programming Language :: Python :: 3.9
Classifier: Programming Language :: Python :: 3.10
Classifier: Programming Language :: Python :: 3.11
Classifier: Programming Language :: Python :: 3.12
Requires-Python: >=3.12
Requires-Dist: aiohttp~=3.8
Requires-Dist: nacos-sdk-python~=2.0
Requires-Dist: pydantic~=2.10
Provides-Extra: config
Requires-Dist: yamlpyconfig~=0.1; extra == 'config'
Provides-Extra: dev
Requires-Dist: aresponses~=3.0; extra == 'dev'
Requires-Dist: black~=25.11; extra == 'dev'
Requires-Dist: mypy~=1.18; extra == 'dev'
Requires-Dist: pytest-asyncio~=1.3; extra == 'dev'
Requires-Dist: pytest-cov~=7.0; extra == 'dev'
Requires-Dist: pytest~=9.0; extra == 'dev'
Requires-Dist: ruff~=0.14; extra == 'dev'
